[
  {
    "op": "replace",
    "path": "/pattern",
    "value": [
      [
        "################",
        "################",
        "################",
        "################",
        "################",
        "################",
        "################",
        "################",
        "################",
        "################",
        "################",
        "################",
        "################"
      ],
      [
        "################",
        "################",
        "################",
        "################",
        "################",
        "################",
        "################",
        "################",
        "################",
        "################",
        "################",
        "############____",
        "________________"
      ]
    ],
    "file": "game:recipes/clayforming/fourcrock.json",
    "condition": { "when": "LazyKnappingClayformingEnabled", "isValue": "true" }
  }
]